LICENSE
MANIFEST.in
README.md
setup.py
cozy_management/__init__.py
cozy_management/backup.py
cozy_management/cli.py
cozy_management/compare_version.py
cozy_management/couchdb.py
cozy_management/diag.py
cozy_management/helpers.py
cozy_management/migration.py
cozy_management/monitor.py
cozy_management/process.py
cozy_management/ssl.py
cozy_management/weboob.py
cozy_management.egg-info/PKG-INFO
cozy_management.egg-info/SOURCES.txt
cozy_management.egg-info/dependency_links.txt
cozy_management.egg-info/entry_points.txt
cozy_management.egg-info/pbr.json
cozy_management.egg-info/requires.txt
cozy_management.egg-info/top_level.txt
extras/acme_tiny/acme_tiny.py
extras/bash_completion/cozy_management