Metadata-Version: 1.1
Name: cozy-management
Version: 0.0.25
Summary: Module to help self hosted cozy management
Home-page: https://github.com/cozy/python_cozy_management
Author: Cozy Cloud
Author-email: contact@cozycloud.cc
License: LGPL
Keywords: cozy
Platform: UNKNOWN
Classifier: Development Status :: 3 - Alpha
Classifier: Environment :: Console
Classifier: License :: OSI Approved :: GNU Library or Lesser General Public License (LGPL)
Classifier: Operating System :: Unix
Classifier: Operating System :: POSIX
Classifier: Programming Language :: Python
Classifier: Programming Language :: Python :: 2.5
Classifier: Programming Language :: Python :: 2.6
Classifier: Programming Language :: Python :: 2.7
Classifier: Topic :: System :: Software Distribution
Classifier: Topic :: System :: Systems Administration
